streamlog/__init__.py
streamlog/streamlog.py
tests/__init__.py
tests/test_simple.py
streamlog-3.0.0.dist-info/LICENSE
streamlog-3.0.0.dist-info/METADATA
streamlog-3.0.0.dist-info/WHEEL
streamlog-3.0.0.dist-info/top_level.txt
streamlog-3.0.0.dist-info/RECORD
