Metadata-Version: 2.1
Name: streamlog
Version: 3.0.0
Summary: A Python package to send print statements to an API while printing to the console.
Home-page: https://github.com/PrathmeShsoni/StreamLog
Author: Prathmesh Soni
Author-email: info@soniprathmesh.com
License: MIT
Keywords: streamlog stream log api print
Classifier: Programming Language :: Python :: 3
Classifier: License :: OSI Approved :: MIT License
Classifier: Operating System :: OS Independent
Requires-Python: >=3.6
License-File: LICENSE
Requires-Dist: pytz
Requires-Dist: requests
Requires-Dist: lxml
